winfuncs/KeyboardHookProc.dll
winfuncs/WinFuncs.dll
winfuncs/__init__.py
winfuncs/_winfuncs.py
winfuncs-0.1.3.dist-info/LICENSE
winfuncs-0.1.3.dist-info/METADATA
winfuncs-0.1.3.dist-info/WHEEL
winfuncs-0.1.3.dist-info/top_level.txt
winfuncs-0.1.3.dist-info/RECORD
